README.txt
setup.cfg
setup.py
Products/__init__.py
Products.CurrencyUtility.egg-info/PKG-INFO
Products.CurrencyUtility.egg-info/SOURCES.txt
Products.CurrencyUtility.egg-info/dependency_links.txt
Products.CurrencyUtility.egg-info/entry_points.txt
Products.CurrencyUtility.egg-info/namespace_packages.txt
Products.CurrencyUtility.egg-info/not-zip-safe
Products.CurrencyUtility.egg-info/requires.txt
Products.CurrencyUtility.egg-info/top_level.txt
Products/CurrencyUtility/__init__.py
Products/CurrencyUtility/config.py
Products/CurrencyUtility/configure.zcml
Products/CurrencyUtility/cron.py
Products/CurrencyUtility/currencies.py
Products/CurrencyUtility/currency.py
Products/CurrencyUtility/interfaces.py
Products/CurrencyUtility/setuphandlers.py
Products/CurrencyUtility/utility.py
Products/CurrencyUtility/browser/__init__.py
Products/CurrencyUtility/browser/configure.zcml
Products/CurrencyUtility/browser/currency_configlet.pt
Products/CurrencyUtility/browser/currency_configlet.py
Products/CurrencyUtility/browser/currency_icon.gif
Products/CurrencyUtility/browser/currency_selector.pt
Products/CurrencyUtility/browser/currency_selector.py
Products/CurrencyUtility/i18n/CurrencyUtility-de-plone.po
Products/CurrencyUtility/i18n/CurrencyUtility-de.po
Products/CurrencyUtility/i18n/CurrencyUtility-fr-plone.po
Products/CurrencyUtility/i18n/CurrencyUtility-fr.po
Products/CurrencyUtility/profiles/default/actionicons.xml
Products/CurrencyUtility/profiles/default/controlpanel.xml
Products/CurrencyUtility/profiles/default/currencyutility_various.txt
Products/CurrencyUtility/profiles/default/import_steps.xml
Products/CurrencyUtility/profiles/default/memberdata_properties.xml
Products/CurrencyUtility/profiles/default/metadata.xml
Products/CurrencyUtility/profiles/default/propertiestool.xml
Products/CurrencyUtility/profiles/default/skins.xml
Products/CurrencyUtility/skins/CurrencyUtility/additional_memberdata.pt
docs/HISTORY.txt